adonai/__init__.py
adonai/algorithm.py
adonai/app.py
adonai/applogger.py
adonai/batch.py
adonai/parser.py
adonai/test.py
adonai/utils.py
adonai-0.0.2.dist-info/licenses/LICENSE
adonai-0.0.2.dist-info/METADATA
adonai-0.0.2.dist-info/WHEEL
adonai-0.0.2.dist-info/entry_points.txt
adonai-0.0.2.dist-info/top_level.txt
adonai-0.0.2.dist-info/RECORD
