Metadata-Version: 2.4
Name: adonai
Version: 0.0.2
Summary: Compute the Approximate Chromatic Number for undirected graph encoded in DIMACS format.
Home-page: https://github.com/frankvegadelgado/adonai
Author: Frank Vega
Author-email: vega.frank@gmail.com
License: MIT License
Project-URL: Source Code, https://github.com/frankvegadelgado/adonai
Classifier: Topic :: Scientific/Engineering
Classifier: Topic :: Software Development
Classifier: Development Status :: 5 - Production/Stable
Classifier: License :: OSI Approved :: MIT License
Classifier: Programming Language :: Python :: 3.12
Classifier: Environment :: Console
Classifier: Intended Audience :: Developers
Classifier: Intended Audience :: Education
Classifier: Intended Audience :: Information Technology
Classifier: Intended Audience :: Science/Research
Classifier: Natural Language :: English
Requires-Python: >=3.12
License-File: LICENSE
Requires-Dist: furones>=0.1.2
Dynamic: author
Dynamic: author-email
Dynamic: classifier
Dynamic: description
Dynamic: description-content-type
Dynamic: home-page
Dynamic: license
Dynamic: license-file
Dynamic: project-url
Dynamic: requires-dist
Dynamic: requires-python
Dynamic: summary
